MANIFEST.in
README.rst
bootstrap-buildout.py
buildout.cfg
setup.py
version.txt
bob/__init__.py
bob.thesis.ichingo2015.egg-info/PKG-INFO
bob.thesis.ichingo2015.egg-info/SOURCES.txt
bob.thesis.ichingo2015.egg-info/dependency_links.txt
bob.thesis.ichingo2015.egg-info/entry_points.txt
bob.thesis.ichingo2015.egg-info/namespace_packages.txt
bob.thesis.ichingo2015.egg-info/requires.txt
bob.thesis.ichingo2015.egg-info/top_level.txt
bob.thesis.ichingo2015.egg-info/zip-safe
bob/thesis/__init__.py
bob/thesis/ichingo2015/__init__.py
bob/thesis/ichingo2015/helpers/__init__.py
bob/thesis/ichingo2015/helpers/database.py
bob/thesis/ichingo2015/helpers/gmm_operations.py
bob/thesis/ichingo2015/helpers/score_manipulate.py
bob/thesis/ichingo2015/helpers/utils.py
bob/thesis/ichingo2015/script/__init__.py
bob/thesis/ichingo2015/script/score_evaluation_crossdb.py
bob/thesis/ichingo2015/script/clientspec/__init__.py
bob/thesis/ichingo2015/script/clientspec/naive_likelihood_sorted_cohortmodels.py
bob/thesis/ichingo2015/script/clientspec/scores_box_plot.py
bob/thesis/ichingo2015/script/clientspec/sort_cohort_models_kl.py
bob/thesis/ichingo2015/script/clientspec/sort_cohort_models_reynolds.py
bob/thesis/ichingo2015/script/clientspec/svm_clientspec_eval.py
bob/thesis/ichingo2015/script/clientspec/svm_clientspec_eval_impostors.py
bob/thesis/ichingo2015/script/clientspec/svm_clientspec_train.py
bob/thesis/ichingo2015/script/clientspec/svmapprox_clientspec_eval.py
bob/thesis/ichingo2015/script/clientspec/svmapprox_clientspec_eval_impostors.py
bob/thesis/ichingo2015/script/clientspec/svmapprox_clientspec_train.py
bob/thesis/ichingo2015/script/clientspec/svmapprox_eval.py
bob/thesis/ichingo2015/script/clientspec/svmapprox_train.py
bob/thesis/ichingo2015/script/clientspec/svmeval.py
bob/thesis/ichingo2015/script/clientspec/svmtrain.py
bob/thesis/ichingo2015/script/diverse/__init__.py
bob/thesis/ichingo2015/script/diverse/replay_attack_frames.py
bob/thesis/ichingo2015/script/fusion/__init__.py
bob/thesis/ichingo2015/script/fusion/and_decision_epsc.py
bob/thesis/ichingo2015/script/fusion/and_decision_epsc_cs.py
doc/conf.py
doc/index.rst
doc/part1.rst
doc/part2.rst
doc/part3.rst
doc/part4.rst
doc/reference.rst
doc/userguide.rst