Metadata-Version: 1.0
Name: bob.thesis.ichingo2015
Version: 0.0.1
Summary: Trustworthy biometric recognition under spoofing attacks: application to the face mode
Home-page: http://pypi.python.org/pypi/bob.thesis.ichingo2015
Author: Ivana Chingovska
Author-email: ivana.chingovska@idiap.ch
License: GPLv3
Keywords: antispoofing,face spoofing attacks,face spoofing database,bob,client-specific anti-spoofing,spoofing evaluation
Platform: UNKNOWN
